gvmrpc/__init__.py
gvmrpc/__version__.py
gvmrpc/client.py
gvmrpc/server.py
gvmrpc-0.1.0.dist-info/licenses/LICENSE
gvmrpc-0.1.0.dist-info/METADATA
gvmrpc-0.1.0.dist-info/WHEEL
gvmrpc-0.1.0.dist-info/entry_points.txt
gvmrpc-0.1.0.dist-info/top_level.txt
gvmrpc-0.1.0.dist-info/RECORD
