Metadata-Version: 2.4
Name: gvmrpc
Version: 0.1.0
Summary: GVM RPC Server and Client
Author-email: Ben Nassif <bennassif@gmail.com>
License-Expression: MIT
Project-URL: homepage, https://github.com/bnassif/gvm-rpc
Project-URL: issues, https://github.com/bnassif/gvm-rpc/issues
Keywords: greenbone,rpc,gvm,server,client
Classifier: Intended Audience :: Developers
Classifier: Natural Language :: English
Classifier: Operating System :: OS Independent
Classifier: Topic :: Software Development
Classifier: Programming Language :: Python :: 3
Requires-Python: >=3.10
License-File: LICENSE
Requires-Dist: lxml
Requires-Dist: python-gvm
Dynamic: license-file
